kworker/__init__.py
kworker/api.py
kworker/exceptions.py
kworker-0.1.2.dist-info/METADATA
kworker-0.1.2.dist-info/WHEEL
kworker-0.1.2.dist-info/top_level.txt
kworker-0.1.2.dist-info/RECORD
