Metadata-Version: 2.4
Name: kworker
Version: 0.1.2
Summary: Асинхронный клиент для взаимодействия с закрытым API kwork.ru
Author-email: tinokil <zemedeuk@gmail.com>
Maintainer-email: tinokil <zemedeuk@gmail.com>
License: MIT
Project-URL: Homepage, https://github.com/Tinokil/kworker
Project-URL: Bug Reports, https://github.com/Tinokil/kworker/issues
Project-URL: Repository, https://github.com/Tinokil/kworker
Project-URL: Changelog, https://github.com/Tinokil/kworker/blob/main/CHANGELOG.md
Project-URL: Releases, https://github.com/Tinokil/kworker/releases
Classifier: Development Status :: 3 - Alpha
Classifier: Intended Audience :: Developers
Classifier: License :: OSI Approved :: MIT License
Classifier: Programming Language :: Python :: 3 :: Only
Classifier: Programming Language :: Python :: 3.10
Classifier: Programming Language :: Python :: 3.11
Classifier: Programming Language :: Python :: 3.12
Classifier: Programming Language :: Python :: 3.13
Classifier: Framework :: Pydantic
Classifier: Framework :: Pydantic :: 2
Classifier: Framework :: AsyncIO
Requires-Python: >=3.10
Requires-Dist: aiohttp>=3.12.0
Requires-Dist: aiohttp-socks>=0.10.0
Requires-Dist: pydantic>=2.11.0
